teams_util/__init__.py
teams_util/teams.py
david_teams_util-1.0.5.dist-info/METADATA
david_teams_util-1.0.5.dist-info/WHEEL
david_teams_util-1.0.5.dist-info/entry_points.txt
david_teams_util-1.0.5.dist-info/top_level.txt
david_teams_util-1.0.5.dist-info/RECORD
