Metadata-Version: 2.4
Name: david-teams-util
Version: 1.0.5
Summary: david's teams util
Home-page: https://github.com/simon-asis/teams_util
Author: david
Author-email: tingyoon@gmail.com
Classifier: Programming Language :: Python :: 3
Classifier: Operating System :: OS Independent
Requires-Python: >=3.8,<=3.12
Requires-Dist: boto3<2.0,>=1.20.0
Provides-Extra: extra
Dynamic: author
Dynamic: author-email
Dynamic: classifier
Dynamic: description
Dynamic: description-content-type
Dynamic: home-page
Dynamic: provides-extra
Dynamic: requires-dist
Dynamic: requires-python
Dynamic: summary
